{"version":1,"resource":"vscode-userdata:/home/bap/.config/Code/User/settings.json","entries":[{"id":"sry0.json","timestamp":1772836550257},{"id":"eL2U.json","timestamp":1772836951398},{"id":"Vzq0.json","timestamp":1772837344826},{"id":"VWPQ.json","timestamp":1772837369106},{"id":"oniu.json","timestamp":1772837416054},{"id":"93nV.json","timestamp":1772837556212},{"id":"tZ3C.json","timestamp":1772837604606},{"id":"ONnw.json","timestamp":1772837862474},{"id":"dwGK.json","source":"undoRedo.source","timestamp":1772837905786},{"id":"QMcx.json","source":"Chỉnh sửa trò chuyện: „/fix Đã mong đợi kết thúc tệp.“","timestamp":1772837956986},{"id":"7AqC.json","timestamp":1772838308780},{"id":"czQ0.json","timestamp":1772976448855},{"id":"IKxY.json","timestamp":1772976875916},{"id":"QFl3.json","timestamp":1772976906365},{"id":"fpSV.json","timestamp":1772979902047},{"id":"f4qG.json","timestamp":1773403663053}]}